pyfluent_iterables/__init__.py
pyfluent_iterables/fluent.py
pyfluent_iterables/py.typed
pyfluent_iterables-2.0.2.dist-info/LICENSE
pyfluent_iterables-2.0.2.dist-info/METADATA
pyfluent_iterables-2.0.2.dist-info/WHEEL
pyfluent_iterables-2.0.2.dist-info/RECORD
