Metadata-Version: 2.3
Name: pyfluent-iterables
Version: 2.0.2
Summary: Fluent API wrapper for Python collections
License: MIT
Keywords: wrapper,fluent,interface,functional,collections
Author: Jan Michelfeit
Requires-Python: >=3.10,<4.0
Classifier: License :: OSI Approved :: MIT License
Classifier: Programming Language :: Python :: 3
Classifier: Programming Language :: Python :: 3.10
Classifier: Programming Language :: Python :: 3.11
Classifier: Programming Language :: Python :: 3.12
Classifier: Programming Language :: Python :: 3.13
Project-URL: Documentation, https://github.com/feynmanix/pyfluent-iterables/blob/main/README.md
Project-URL: Repository, https://github.com/feynmanix/pyfluent-iterables
